<?xml version="1.0"?>
<objecttypes xmlns:xsi="http://www.w3.org/2001/XMLSchema-instance" xmlns:xsd="http://www.w3.org/2001/XMLSchema">
  <objecttype name="Chicken1Enemy">
    <property name="DisplayName" type="string" default="Chicken" />
    <property name="IsFlying" type="bool" default="false" />
    <property name="HasLightSource" type="bool" default="false" />
    <property name="SpriteInstanceCurrentChainName" type="string" />
    <property name="IsJumper" type="bool" default="false" />
  </objecttype>
  <objecttype name="Chicken2Enemy">
    <property name="DisplayName" type="string" default="Enraged Chicken" />
    <property name="IsFlying" type="bool" default="false" />
    <property name="HasLightSource" type="bool" default="false" />
    <property name="SpriteInstanceCurrentChainName" type="string" />
    <property name="IsJumper" type="bool" default="false" />
  </objecttype>
  <objecttype name="Chicken3Enemy">
    <property name="DisplayName" type="string" default="Dragon" />
    <property name="IsFlying" type="bool" default="true" />
    <property name="HasLightSource" type="bool" default="true" />
    <property name="SpriteInstanceCurrentChainName" type="string" />
    <property name="IsJumper" type="bool" default="false" />
  </objecttype>
  <objecttype name="Cow1Enemy">
    <property name="DisplayName" type="string" default="Cow" />
    <property name="IsFlying" type="bool" default="false" />
    <property name="HasLightSource" type="bool" default="false" />
    <property name="SpriteInstanceCurrentChainName" type="string" />
    <property name="IsJumper" type="bool" default="false" />
  </objecttype>
  <objecttype name="Cow2Enemy">
    <property name="DisplayName" type="string" default="Unusual Cow" />
    <property name="IsFlying" type="bool" default="false" />
    <property name="HasLightSource" type="bool" default="false" />
    <property name="SpriteInstanceCurrentChainName" type="string" />
    <property name="IsJumper" type="bool" default="false" />
  </objecttype>
  <objecttype name="Cow3Enemy">
    <property name="DisplayName" type="string" default="Hybrid Cowman" />
    <property name="IsFlying" type="bool" default="false" />
    <property name="HasLightSource" type="bool" default="false" />
    <property name="SpriteInstanceCurrentChainName" type="string" />
    <property name="IsJumper" type="bool" default="false" />
  </objecttype>
  <objecttype name="Pig1Enemy">
    <property name="DisplayName" type="string" default="Pig" />
    <property name="IsFlying" type="bool" default="false" />
    <property name="HasLightSource" type="bool" default="false" />
    <property name="SpriteInstanceCurrentChainName" type="string" />
    <property name="IsJumper" type="bool" default="false" />
  </objecttype>
  <objecttype name="Pig2Enemy">
    <property name="DisplayName" type="string" default="Mutant Pig" />
    <property name="IsFlying" type="bool" default="false" />
    <property name="HasLightSource" type="bool" default="false" />
    <property name="SpriteInstanceCurrentChainName" type="string" />
    <property name="IsJumper" type="bool" default="false" />
  </objecttype>
  <objecttype name="Pig3Enemy">
    <property name="DisplayName" type="string" default="Juggernaut Pig" />
    <property name="IsFlying" type="bool" default="false" />
    <property name="HasLightSource" type="bool" default="false" />
    <property name="SpriteInstanceCurrentChainName" type="string" />
    <property name="IsJumper" type="bool" default="false" />
  </objecttype>
  <objecttype name="Rabbit1Enemy">
    <property name="DisplayName" type="string" default="Rabbit" />
    <property name="IsFlying" type="bool" default="false" />
    <property name="HasLightSource" type="bool" default="false" />
    <property name="SpriteInstanceCurrentChainName" type="string" />
    <property name="IsJumper" type="bool" default="true" />
  </objecttype>
  <objecttype name="Rabbit2Enemy">
    <property name="DisplayName" type="string" default="Abnormal Rabbit" />
    <property name="IsFlying" type="bool" default="false" />
    <property name="HasLightSource" type="bool" default="false" />
    <property name="SpriteInstanceCurrentChainName" type="string" />
    <property name="IsJumper" type="bool" default="false" />
  </objecttype>
  <objecttype name="Rabbit3Enemy">
    <property name="DisplayName" type="string" default="Athletic Rabbit" />
    <property name="IsFlying" type="bool" default="false" />
    <property name="HasLightSource" type="bool" default="false" />
    <property name="SpriteInstanceCurrentChainName" type="string" />
    <property name="IsJumper" type="bool" default="false" />
  </objecttype>
  <objecttype name="Sheep1Enemy">
    <property name="DisplayName" type="string" default="Sheep" />
    <property name="IsFlying" type="bool" default="false" />
    <property name="HasLightSource" type="bool" default="false" />
    <property name="SpriteInstanceCurrentChainName" type="string" />
    <property name="IsJumper" type="bool" default="false" />
  </objecttype>
  <objecttype name="Sheep2Enemy">
    <property name="DisplayName" type="string" default="Deformed Sheep" />
    <property name="IsFlying" type="bool" default="false" />
    <property name="HasLightSource" type="bool" default="false" />
    <property name="SpriteInstanceCurrentChainName" type="string" />
    <property name="IsJumper" type="bool" default="false" />
  </objecttype>
  <objecttype name="Sheep3Enemy">
    <property name="DisplayName" type="string" default="Sheep Demoness" />
    <property name="IsFlying" type="bool" default="false" />
    <property name="HasLightSource" type="bool" default="false" />
    <property name="SpriteInstanceCurrentChainName" type="string" />
    <property name="IsJumper" type="bool" default="false" />
  </objecttype>
  <objecttype name="StructurePlacement">
    <property name="SpriteInstanceRed" type="float" default="0" />
    <property name="SpriteInstanceGreen" type="float" default="1" />
    <property name="SpriteInstanceBlue" type="float" default="0" />
    <property name="SpriteInstanceColorOperation" type="ColorOperation" default="ColorTextureAlpha" />
    <property name="SpriteInstanceTextureScale" type="float" default="1" />
    <property name="SpriteInstanceAnimate" type="bool" default="true" />
    <property name="SpriteInstanceAlpha" type="float" default="1" />
  </objecttype>
  <objecttype name="TileCollisionCircle">
    <property name="Altitude" type="float" />
    <property name="CircleInstanceRadius" type="float" default="64" />
    <property name="ZHeight" type="float" />
  </objecttype>
  <objecttype name="TileCollisionRectangle">
    <property name="AxisAlignedRectangleInstanceWidth" type="float" default="128" />
    <property name="AxisAlignedRectangleInstanceHeight" type="float" default="128" />
  </objecttype>
  <objecttype name="TiledOverlay">
    <property name="ChainName" type="string" />
  </objecttype>
  <objecttype name="CannonProjectile">
    <property name="DamageInflicted" type="float" default="1" />
    <property name="HasLightSource" type="bool" default="false" />
    <property name="Mass" type="float" default="0.5" />
  </objecttype>
  <objecttype name="ChemicalProjectile">
    <property name="DamageInflicted" type="float" />
    <property name="HasLightSource" type="bool" default="true" />
    <property name="Mass" type="float" default="0.05" />
  </objecttype>
  <objecttype name="ElectricProjectile">
    <property name="DamageInflicted" type="float" />
    <property name="HasLightSource" type="bool" default="true" />
    <property name="Mass" type="float" default="0.001" />
  </objecttype>
  <objecttype name="FireProjectile">
    <property name="DamageInflicted" type="float" />
    <property name="HasLightSource" type="bool" default="true" />
    <property name="Mass" type="float" default="0.02" />
  </objecttype>
  <objecttype name="FrostProjectile">
    <property name="DamageInflicted" type="float" />
    <property name="HasLightSource" type="bool" default="true" />
    <property name="Mass" type="float" default="0.005" />
  </objecttype>
  <objecttype name="PiercingProjectile">
    <property name="DamageInflicted" type="float" />
    <property name="HasLightSource" type="bool" default="false" />
    <property name="Mass" type="float" default="0.05" />
  </objecttype>
  <objecttype name="BombardingTower">
    <property name="DisplayName" type="string" default="Cannon" />
    <property name="HasLightSource" type="bool" default="false" />
    <property name="StructureDescription" type="string" />
    <property name="ProjectileSpeed" type="float" default="800" />
    <property name="RangedRadius" type="float" default="850" />
    <property name="AttackDamage" type="float" default="60" />
    <property name="SecondsBetweenFiring" type="float" default="6" />
    <property name="ProjectileAltitude" type="float" default="100" />
    <property name="HasSplashDamage" type="bool" default="true" />
    <property name="SlowsEnemies" type="bool" />
    <property name="StunsEnemies" type="bool" />
    <property name="MinimumRangeRadius" type="float" default="450" />
    <property name="StatusEffectSeconds" type="float" default="0" />
    <property name="StatusDamageMultiplier" type="float" default="0" />
    <property name="SatoshiCost" type="int" default="20" />
  </objecttype>
  <objecttype name="ChemicalTower">
    <property name="DisplayName" type="string" default="Chemical" />
    <property name="HasLightSource" type="bool" default="true" />
    <property name="StructureDescription" type="string" />
    <property name="ProjectileSpeed" type="float" default="750" />
    <property name="RangedRadius" type="float" default="450" />
    <property name="AttackDamage" type="float" default="2" />
    <property name="SecondsBetweenFiring" type="float" default="3" />
    <property name="ProjectileAltitude" type="float" default="100" />
    <property name="HasSplashDamage" type="bool" default="false" />
    <property name="SlowsEnemies" type="bool" default="true" />
    <property name="StunsEnemies" type="bool" />
    <property name="MinimumRangeRadius" type="float" default="150" />
    <property name="StatusEffectSeconds" type="float" default="5" />
    <property name="StatusDamageMultiplier" type="float" default="3.5" />
    <property name="SatoshiCost" type="int" default="12" />
  </objecttype>
  <objecttype name="ElectricTower">
    <property name="DisplayName" type="string" default="Electric" />
    <property name="HasLightSource" type="bool" default="true" />
    <property name="StructureDescription" type="string" />
    <property name="ProjectileSpeed" type="float" default="1500" />
    <property name="RangedRadius" type="float" default="650" />
    <property name="AttackDamage" type="float" default="50" />
    <property name="SecondsBetweenFiring" type="float" default="5" />
    <property name="ProjectileAltitude" type="float" default="100" />
    <property name="HasSplashDamage" type="bool" />
    <property name="SlowsEnemies" type="bool" />
    <property name="StunsEnemies" type="bool" default="true" />
    <property name="MinimumRangeRadius" type="float" default="75" />
    <property name="StatusEffectSeconds" type="float" default="2" />
    <property name="StatusDamageMultiplier" type="float" default="0" />
    <property name="SatoshiCost" type="int" default="15" />
  </objecttype>
  <objecttype name="FireTower">
    <property name="DisplayName" type="string" default="Fire" />
    <property name="HasLightSource" type="bool" default="true" />
    <property name="StructureDescription" type="string" />
    <property name="ProjectileSpeed" type="float" default="800" />
    <property name="RangedRadius" type="float" default="550" />
    <property name="AttackDamage" type="float" default="15" />
    <property name="SecondsBetweenFiring" type="float" default="2" />
    <property name="ProjectileAltitude" type="float" default="100" />
    <property name="HasSplashDamage" type="bool" />
    <property name="SlowsEnemies" type="bool" />
    <property name="StunsEnemies" type="bool" />
    <property name="MinimumRangeRadius" type="float" default="100" />
    <property name="StatusEffectSeconds" type="float" default="2" />
    <property name="StatusDamageMultiplier" type="float" default="0.15" />
    <property name="SatoshiCost" type="int" default="12" />
  </objecttype>
  <objecttype name="FrostTower">
    <property name="DisplayName" type="string" default="Frost" />
    <property name="HasLightSource" type="bool" default="true" />
    <property name="StructureDescription" type="string" />
    <property name="ProjectileSpeed" type="float" default="500" />
    <property name="RangedRadius" type="float" default="500" />
    <property name="AttackDamage" type="float" default="20" />
    <property name="SecondsBetweenFiring" type="float" default="2.5" />
    <property name="ProjectileAltitude" type="float" default="100" />
    <property name="HasSplashDamage" type="bool" />
    <property name="SlowsEnemies" type="bool" default="true" />
    <property name="StunsEnemies" type="bool" />
    <property name="MinimumRangeRadius" type="float" default="100" />
    <property name="StatusEffectSeconds" type="float" default="5" />
    <property name="StatusDamageMultiplier" type="float" default="0.05" />
    <property name="SatoshiCost" type="int" default="8" />
  </objecttype>
  <objecttype name="PiercingTower">
    <property name="DisplayName" type="string" default="Arrow" />
    <property name="HasLightSource" type="bool" default="false" />
    <property name="StructureDescription" type="string" />
    <property name="ProjectileSpeed" type="float" default="1200" />
    <property name="RangedRadius" type="float" default="600" />
    <property name="AttackDamage" type="float" default="30" />
    <property name="SecondsBetweenFiring" type="float" default="3" />
    <property name="ProjectileAltitude" type="float" default="25" />
    <property name="HasSplashDamage" type="bool" />
    <property name="SlowsEnemies" type="bool" />
    <property name="StunsEnemies" type="bool" />
    <property name="MinimumRangeRadius" type="float" default="250" />
    <property name="StatusEffectSeconds" type="float" default="0" />
    <property name="StatusDamageMultiplier" type="float" default="0" />
    <property name="SatoshiCost" type="int" default="10" />
  </objecttype>
</objecttypes>